gym_algorithmic/__init__.py
gym_algorithmic/algorithmic_env.py
gym_algorithmic/copy_.py
gym_algorithmic/duplicated_input.py
gym_algorithmic/repeat_copy.py
gym_algorithmic/reverse.py
gym_algorithmic/reversed_addition.py
gym_algorithmic-0.0.1.dist-info/METADATA
gym_algorithmic-0.0.1.dist-info/WHEEL
gym_algorithmic-0.0.1.dist-info/top_level.txt
gym_algorithmic-0.0.1.dist-info/RECORD
