Metadata-Version: 2.1
Name: gym-algorithmic
Version: 0.0.1
Summary: Algorithmic Environments from OpenAI Gym
Home-page: https://github.com/Rohan138/gym-algorithmic
Author: Rohan Potdar
Author-email: rohanpotdar138@gmail.com
License: UNKNOWN
Platform: UNKNOWN
Classifier: Programming Language :: Python :: 3
Classifier: Programming Language :: Python :: 3.6
Classifier: Programming Language :: Python :: 3.7
Classifier: Programming Language :: Python :: 3.8
Classifier: Programming Language :: Python :: 3.9
Requires-Python: >=3.6, <3.10
Requires-Dist: gym (>=0.19.0)
